active_request/__init__.py
active_request-2025.9.152128.dist-info/licenses/LICENSE
active_request-2025.9.152128.dist-info/METADATA
active_request-2025.9.152128.dist-info/WHEEL
active_request-2025.9.152128.dist-info/top_level.txt
active_request-2025.9.152128.dist-info/RECORD
