Metadata-Version: 2.4
Name: active_request
Version: 2025.9.152128
Summary: Sliding-window active request counter (last 60s) using Redis for FastAPI or any Python app.
Home-page: https://github.com/chigwell/active_request
Author: Eugene Evstafev
Author-email: chigwel@gmail.com
License: MIT
Classifier: License :: OSI Approved :: MIT License
Classifier: Development Status :: 3 - Alpha
Classifier: Intended Audience :: Developers
Classifier: Programming Language :: Python :: 3
Classifier: Operating System :: OS Independent
Requires-Python: >=3.8
License-File: LICENSE
Requires-Dist: redis>=5.0.0
Dynamic: author
Dynamic: author-email
Dynamic: classifier
Dynamic: description
Dynamic: description-content-type
Dynamic: home-page
Dynamic: license
Dynamic: license-file
Dynamic: requires-dist
Dynamic: requires-python
Dynamic: summary
